mo_sql_parsing/__init__.py
mo_sql_parsing/formatting.py
mo_sql_parsing/keywords.py
mo_sql_parsing/sql_parser.py
mo_sql_parsing/types.py
mo_sql_parsing/utils.py
mo_sql_parsing/windows.py
mo_sql_parsing-11.663.25011.dist-info/LICENSE
mo_sql_parsing-11.663.25011.dist-info/METADATA
mo_sql_parsing-11.663.25011.dist-info/WHEEL
mo_sql_parsing-11.663.25011.dist-info/top_level.txt
mo_sql_parsing-11.663.25011.dist-info/zip-safe
mo_sql_parsing-11.663.25011.dist-info/RECORD
