Metadata-Version: 2.2
Name: mo-sql-parsing
Version: 11.663.25011
Summary: More SQL Parsing! Parse SQL into JSON parse tree
Home-page: https://github.com/klahnakoski/mo-sql-parsing
Author: Kyle Lahnakoski
Author-email: kyle@lahnakoski.com
License: MPL 2.0
Classifier: Development Status :: 5 - Production/Stable
Classifier: Topic :: Software Development :: Libraries
Classifier: Topic :: Software Development :: Libraries :: Python Modules
Classifier: License :: OSI Approved :: Mozilla Public License 2.0 (MPL 2.0)
Classifier: Programming Language :: SQL
Classifier: Programming Language :: Python :: 3.8
Classifier: Programming Language :: Python :: 3.9
Classifier: Programming Language :: Python :: 3.10
Classifier: Programming Language :: Python :: 3.11
Classifier: Programming Language :: Python :: 3.12
Classifier: Programming Language :: Python :: 3.13
License-File: LICENSE
Requires-Dist: mo-dots==10.659.25005
Requires-Dist: mo-future==7.584.24095
Requires-Dist: mo-imports==7.584.24095
Requires-Dist: mo-parsing==8.661.25011
Provides-Extra: tests
Requires-Dist: mo-testing==7.562.24075; extra == "tests"
Requires-Dist: mo-threads==6.570.24076; extra == "tests"
Requires-Dist: mo-files==6.570.24076; extra == "tests"
Requires-Dist: mo-streams==1.570.24076; extra == "tests"
Requires-Dist: zstandard>=0.23.0; extra == "tests"
Requires-Dist: psutil>=6.1.1; extra == "tests"
Requires-Dist: objgraph>=3.6.2; extra == "tests"
Requires-Dist: pympler; extra == "tests"
Dynamic: author
Dynamic: author-email
Dynamic: classifier
Dynamic: description
Dynamic: description-content-type
Dynamic: home-page
Dynamic: license
Dynamic: provides-extra
Dynamic: requires-dist
Dynamic: summary
